nnabla/utils/converter/onnx/__init__.py
nnabla/utils/converter/onnx/exporter.py
nnabla/utils/converter/onnx/importer.py
nnabla/utils/converter/onnx/utils.py
nnabla/utils/converter/tensorflow/__init__.py
nnabla/utils/converter/tensorflow/common.py
nnabla/utils/converter/tensorflow/exporter.py
nnabla/utils/converter/tensorflow/importer.py
nnabla/utils/converter/tensorflow/parsetab.py
nnabla/utils/converter/tensorflow/refine_graph.py
nnabla/utils/converter/tensorflow/refine_parser.py
nnabla/utils/converter/tflite/__init__.py
nnabla/utils/converter/tflite/exporter.py
nnabla/utils/converter/tflite/flatc_linux
nnabla/utils/converter/tflite/flatc_mac
nnabla/utils/converter/tflite/flatc_windows.exe
nnabla/utils/converter/tflite/importer.py
nnabla/utils/converter/tflite/quantized_converter.py
nnabla/utils/converter/tflite/schema.fbs
nnabla_converter-1.39.0.dist-info/METADATA
nnabla_converter-1.39.0.dist-info/WHEEL
nnabla_converter-1.39.0.dist-info/top_level.txt
nnabla_converter-1.39.0.dist-info/RECORD
