Metadata-Version: 2.1
Name: nnabla_converter
Version: 1.39.0
Summary: NNabla File Format Converter
Home-page: https://github.com/sony/nnabla
Author: Takuya Narihira, Sony Corporation
Author-email: nnabla@googlegroups.com
License: Apache License 2.0
Keywords: NNabla File Format Converter
Classifier: Development Status :: 5 - Production/Stable
Classifier: Intended Audience :: Developers
Classifier: Intended Audience :: Education
Classifier: Intended Audience :: Science/Research
Classifier: Topic :: Scientific/Engineering
Classifier: Topic :: Scientific/Engineering :: Artificial Intelligence
Classifier: License :: OSI Approved :: Apache Software License
Classifier: Programming Language :: Python :: 3.8
Classifier: Programming Language :: Python :: 3.9
Classifier: Programming Language :: Python :: 3.10
Requires-Python: >=3.6
Requires-Dist: tensorflow <2.15.0,>=2.13.0
Requires-Dist: tensorflow-probability <0.23.0,>=0.21.0
Requires-Dist: onnx-tf
Requires-Dist: tf2onnx ~=1.15.1
Requires-Dist: tensorflow-addons
Requires-Dist: onnx ~=1.13.0
Requires-Dist: tflite2onnx
Requires-Dist: flatbuffers
Requires-Dist: pyopenssl
Requires-Dist: nnabla ==1.39.0
